hdwallet/__init__.py
hdwallet/consts.py
hdwallet/crypto.py
hdwallet/exceptions.py
hdwallet/hdwallet.py
hdwallet/info.py
hdwallet/keys.py
hdwallet/slip44.py
hdwallet/symbols.py
hdwallet/utils.py
hdwallet/wif.py
hdwallet/addresses/__init__.py
hdwallet/addresses/algorand.py
hdwallet/addresses/aptos.py
hdwallet/addresses/avalanche.py
hdwallet/addresses/cardano.py
hdwallet/addresses/cosmos.py
hdwallet/addresses/eos.py
hdwallet/addresses/ergo.py
hdwallet/addresses/ethereum.py
hdwallet/addresses/filecoin.py
hdwallet/addresses/harmony.py
hdwallet/addresses/iaddress.py
hdwallet/addresses/icon.py
hdwallet/addresses/injective.py
hdwallet/addresses/monero.py
hdwallet/addresses/multiversx.py
hdwallet/addresses/nano.py
hdwallet/addresses/near.py
hdwallet/addresses/neo.py
hdwallet/addresses/okt_chain.py
hdwallet/addresses/p2pkh.py
hdwallet/addresses/p2sh.py
hdwallet/addresses/p2tr.py
hdwallet/addresses/p2wpkh.py
hdwallet/addresses/p2wpkh_in_p2sh.py
hdwallet/addresses/p2wsh.py
hdwallet/addresses/p2wsh_in_p2sh.py
hdwallet/addresses/ripple.py
hdwallet/addresses/solana.py
hdwallet/addresses/stellar.py
hdwallet/addresses/sui.py
hdwallet/addresses/tezos.py
hdwallet/addresses/tron.py
hdwallet/addresses/xinfin.py
hdwallet/addresses/zilliqa.py
hdwallet/cli/__init__.py
hdwallet/cli/__main__.py
hdwallet/cli/dump.py
hdwallet/cli/dumps.py
hdwallet/cli/generate/__init__.py
hdwallet/cli/generate/entropy.py
hdwallet/cli/generate/mnemonic.py
hdwallet/cli/generate/seed.py
hdwallet/cli/list/__init__.py
hdwallet/cli/list/cryptocurrencies.py
hdwallet/cli/list/languages.py
hdwallet/cli/list/strengths.py
hdwallet/cryptocurrencies/__init__.py
hdwallet/cryptocurrencies/adcoin.py
hdwallet/cryptocurrencies/akashnetwork.py
hdwallet/cryptocurrencies/algorand.py
hdwallet/cryptocurrencies/anon.py
hdwallet/cryptocurrencies/aptos.py
hdwallet/cryptocurrencies/arbitum.py
hdwallet/cryptocurrencies/argoneum.py
hdwallet/cryptocurrencies/artax.py
hdwallet/cryptocurrencies/aryacoin.py
hdwallet-3.6.0.dist-info/LICENSE
hdwallet-3.6.0.dist-info/METADATA
hdwallet-3.6.0.dist-info/WHEEL
hdwallet-3.6.0.dist-info/entry_points.txt
hdwallet-3.6.0.dist-info/top_level.txt
hdwallet-3.6.0.dist-info/RECORD
