Metadata-Version: 2.1
Name: hdwallet
Version: 3.6.0
Summary: Python-based library implementing a Hierarchical Deterministic (HD) Wallet generator for 200+ cryptocurrencies.
Home-page: https://hdwallet.io
Author: Meheret Tesfaye Batu
Author-email: meherett.batu@gmail.com
License: MIT
Project-URL: Tracker, https://github.com/hdwallet-io/python-hdwallet/issues
Project-URL: Source, https://github.com/hdwallet-io/python-hdwallet
Project-URL: Changelog, https://github.com/hdwallet-io/python-hdwallet/blob/master/CHANGELOG.md
Project-URL: Documentation, https://hdwallet.readthedocs.com
Keywords: ecc,kholaw,slip10,ed25519,nist256p1,secp256k1,hd,bip32,bip44,bip49,bip84,bip86,bip141,monero,cardano,entropy,mnemonic,seed,bip39,algorand,electrum,cryptocurrencies,bitcoin,ethereum,cryptography,cli,cip1852
Classifier: Development Status :: 5 - Production/Stable
Classifier: License :: OSI Approved :: MIT License
Classifier: Programming Language :: Python :: 3.9
Classifier: Programming Language :: Python :: 3.10
Classifier: Programming Language :: Python :: 3.11
Classifier: Programming Language :: Python :: 3.12
Classifier: Programming Language :: Python :: 3.13
Classifier: Topic :: Software Development :: Libraries :: Python Modules
Requires-Python: >=3.9,<4
License-File: LICENSE
Requires-Dist: ecdsa <1,>=0.18.0
Requires-Dist: crcmod <2,>=1.7
Requires-Dist: pycryptodome <4,>=3.20
Requires-Dist: ed25519-blake2b <2,>=1.4.1
Requires-Dist: coincurve <21,>=20.0.0
Requires-Dist: pynacl <2,>=1.5.0
Requires-Dist: base58 <3,>=2.1.1
Requires-Dist: cbor2 <6,>=5.6.1
Provides-Extra: cli
Requires-Dist: click <9,>=8.1.7 ; extra == 'cli'
Requires-Dist: click-aliases <2,>=1.0.5 ; extra == 'cli'
Requires-Dist: tabulate <1,>=0.9.0 ; extra == 'cli'
Requires-Dist: bip38 <2,>=1.4.1 ; extra == 'cli'
Provides-Extra: docs
Requires-Dist: sphinx <9,>=8.1.3 ; extra == 'docs'
Requires-Dist: sphinx-click <7,>=6.0.0 ; extra == 'docs'
Requires-Dist: furo ==2024.8.6 ; extra == 'docs'
Provides-Extra: tests
Requires-Dist: pytest <9,>=8.3.2 ; extra == 'tests'
Requires-Dist: coverage <8,>=7.6.4 ; extra == 'tests'
Requires-Dist: tox <5,>=4.23.2 ; extra == 'tests'
